gbstoolkit/__init__.py
gbstoolkit/__main__.py
gbstoolkit/dsl/__init__.py
gbstoolkit/dsl/actor.py
gbstoolkit/dsl/assets.py
gbstoolkit/dsl/datatypes.py
gbstoolkit/dsl/enums.py
gbstoolkit/dsl/event.py
gbstoolkit/dsl/marshalling.py
gbstoolkit/dsl/palette.py
gbstoolkit/dsl/project.py
gbstoolkit/dsl/scene.py
gbstoolkit/dsl/settings.py
gbstoolkit/dsl/trigger.py
gbstoolkit/dsl/util.py
gbstoolkit/dsl/command/__init__.py
gbstoolkit/dsl/command/cmd_actor.py
gbstoolkit/dsl/command/cmd_base.py
gbstoolkit/dsl/command/cmd_camera.py
gbstoolkit/dsl/command/cmd_engine.py
gbstoolkit/dsl/command/cmd_flowcontrol.py
gbstoolkit/dsl/command/cmd_misc.py
gbstoolkit/dsl/command/cmd_scene.py
gbstoolkit/dsl/command/cmd_text.py
gbstoolkit/dsl/command/cmd_timing.py
gbstoolkit/dsl/command/cmd_variable.py
gbstoolkit-1.0.1.dist-info/LICENSE.md
gbstoolkit-1.0.1.dist-info/METADATA
gbstoolkit-1.0.1.dist-info/WHEEL
gbstoolkit-1.0.1.dist-info/entry_points.txt
gbstoolkit-1.0.1.dist-info/top_level.txt
gbstoolkit-1.0.1.dist-info/RECORD
