Metadata-Version: 2.1
Name: gbstoolkit
Version: 1.0.1
Summary: Various Python tools for messing around with GB Studio projects.
Home-page: https://github.com/LemmaEOF/GBSToolkit
Author: LemmaEOF
License: Fuck Around and Find Out License, version 0.2
Project-URL: Bug Tracker, https://github.com/LemmaEOF/GBSToolkit/issues
Platform: UNKNOWN
Classifier: Development Status :: 4 - Beta
Classifier: Intended Audience :: Developers
Classifier: License :: Other/Proprietary License
Classifier: Operating System :: OS Independent
Classifier: Programming Language :: Python :: 3 :: Only
Classifier: Topic :: Software Development :: Build Tools
Classifier: Typing :: Typed
Requires-Python: >3.6
License-File: LICENSE.md
Requires-Dist: kdl-py
